foundry/__init__.py
foundry/__main__.py
foundry/auth.py
foundry/errors.py
foundry/foundry.py
foundry/foundry_cache.py
foundry/foundry_dataset.py
foundry/https_download.py
foundry/https_upload.py
foundry/mdf_client.py
foundry/models.py
foundry/utils.py
foundry/integrations/__init__.py
foundry/integrations/huggingface.py
foundry/jsonschema_models/__init__.py
foundry/jsonschema_models/dc_model.py
foundry/jsonschema_models/project_model.py
foundry/loaders/__init__.py
foundry/loaders/tf_wrapper.py
foundry/loaders/torch_wrapper.py
foundry/mcp/__init__.py
foundry/mcp/server.py
foundry_ml-1.2.1.dist-info/licenses/LICENSE
tests/__init__.py
tests/test_data.py
tests/test_errors.py
tests/test_foundry.py
tests/test_foundry_cache.py
tests/test_foundry_components.py
tests/test_foundry_dataset.py
tests/test_https_download.py
tests/test_new_features.py
tests/data/__init__.py
foundry_ml-1.2.1.dist-info/METADATA
foundry_ml-1.2.1.dist-info/WHEEL
foundry_ml-1.2.1.dist-info/entry_points.txt
foundry_ml-1.2.1.dist-info/top_level.txt
foundry_ml-1.2.1.dist-info/RECORD
