Metadata-Version: 2.4
Name: foundry_ml
Version: 1.2.1
Summary: Package to support simplified application of machine learning models to datasets in materials science
Home-page: https://github.com/MLMI2-CSSI/foundry
Author: Aristana Scourtas, KJ Schmidt, Isaac Darling, Aadit Ambadkar, Braeden Cullen,
Author-email: blaiszik@uchicago.edu
License: MIT License
Keywords: materials science,machine learning,datasets,MCP,AI agents
Classifier: Development Status :: 4 - Beta
Classifier: Intended Audience :: Science/Research
Classifier: License :: OSI Approved :: MIT License
Classifier: Natural Language :: English
Classifier: Operating System :: OS Independent
Classifier: Programming Language :: Python :: 3
Classifier: Programming Language :: Python :: 3.8
Classifier: Programming Language :: Python :: 3.9
Classifier: Programming Language :: Python :: 3.10
Classifier: Programming Language :: Python :: 3.11
Classifier: Programming Language :: Python :: 3.12
Classifier: Topic :: Scientific/Engineering
Requires-Python: >=3.8
License-File: LICENSE
Requires-Dist: mdf_toolbox>=0.7.1
Requires-Dist: globus-sdk<4,>=3
Requires-Dist: mdf_connect_client>=0.5.0
Requires-Dist: requests>=2.31.0
Requires-Dist: tqdm>=4.66.0
Requires-Dist: numpy>=2.0.0
Requires-Dist: pandas>=2.2.2
Requires-Dist: h5py>=3.11.0
Requires-Dist: pydantic>=2.7.2
Requires-Dist: json2table>=1.1.5
Requires-Dist: typer>=0.12.0
Requires-Dist: rich>=13.7.0
Provides-Extra: torch
Requires-Dist: torch>=2.1.0; extra == "torch"
Provides-Extra: tensorflow
Requires-Dist: tensorflow>=2.12.0; extra == "tensorflow"
Provides-Extra: excel
Requires-Dist: openpyxl>=3.1.0; extra == "excel"
Provides-Extra: huggingface
Requires-Dist: datasets>=2.14.0; extra == "huggingface"
Requires-Dist: huggingface_hub>=0.17.0; extra == "huggingface"
Provides-Extra: examples
Requires-Dist: scikit-learn>=1.4.0; extra == "examples"
Provides-Extra: dev
Requires-Dist: pytest>=7.4; extra == "dev"
Requires-Dist: pytest-cov>=4.1; extra == "dev"
Requires-Dist: pytest-mock>=3.12; extra == "dev"
Requires-Dist: flake8>=7.0; extra == "dev"
Requires-Dist: jsonschema>=4.19; extra == "dev"
Requires-Dist: mock>=5.1; extra == "dev"
Dynamic: author
Dynamic: author-email
Dynamic: classifier
Dynamic: description
Dynamic: description-content-type
Dynamic: home-page
Dynamic: keywords
Dynamic: license
Dynamic: license-file
Dynamic: provides-extra
Dynamic: requires-dist
Dynamic: requires-python
Dynamic: summary
